winrt/_winrt_microsoft_ui_xaml_hosting.cp311-win_amd64.pyd
winrt/_winrt_microsoft_ui_xaml_hosting.pyi
winrt/microsoft/ui/xaml/hosting/__init__.py
winrt/microsoft/ui/xaml/hosting/py.typed
winrt_Microsoft.UI.Xaml.Hosting-2.3.0.dist-info/METADATA
winrt_Microsoft.UI.Xaml.Hosting-2.3.0.dist-info/WHEEL
winrt_Microsoft.UI.Xaml.Hosting-2.3.0.dist-info/top_level.txt
winrt_Microsoft.UI.Xaml.Hosting-2.3.0.dist-info/RECORD
